<?xml version="1.0" encoding="utf-8"?>
<NodeSet xmlns:i="http://www.w3.org/2001/XMLSchema-instance" xmlns="http://opcfoundation.org/UA/2008/02/Types.xsd">
  <NamespaceUris>
    <String>http://opcfoundation.org/UA/</String>
    <String>http://microsoft.com/Opc/OpcPlc/Boiler</String>
  </NamespaceUris>
  <ServerUris />
  <Nodes>
    <Node i:type="DataTypeNode">
      <NodeId>
        <Identifier>ns=1;i=15001</Identifier>
      </NodeId>
      <NodeClass>DataType_64</NodeClass>
      <BrowseName>
        <NamespaceIndex>1</NamespaceIndex>
        <Name>BoilerTemperatureType</Name>
      </BrowseName>
      <DisplayName>
        <Locale></Locale>
        <Text>BoilerTemperatureType</Text>
      </DisplayName>
      <Description>
        <Locale></Locale>
        <Text>Temperature in °C next to the heater at the bottom, and away from the heater at the top.</Text>
      </Description>
      <WriteMask>0</WriteMask>
      <UserWriteMask>0</UserWriteMask>
      <RolePermissions />
      <UserRolePermissions />
      <AccessRestrictions>0</AccessRestrictions>
      <References>
        <ReferenceNode>
          <ReferenceTypeId>
            <Identifier>i=45</Identifier>
          </ReferenceTypeId>
          <IsInverse>true</IsInverse>
          <TargetId>
            <Identifier>i=22</Identifier>
          </TargetId>
        </ReferenceNode>
        <ReferenceNode>
          <ReferenceTypeId>
            <Identifier>i=38</Identifier>
          </ReferenceTypeId>
          <IsInverse>false</IsInverse>
          <TargetId>
            <Identifier>ns=1;i=15004</Identifier>
          </TargetId>
        </ReferenceNode>
        <ReferenceNode>
          <ReferenceTypeId>
            <Identifier>i=38</Identifier>
          </ReferenceTypeId>
          <IsInverse>false</IsInverse>
          <TargetId>
            <Identifier>ns=1;i=15008</Identifier>
          </TargetId>
        </ReferenceNode>
        <ReferenceNode>
          <ReferenceTypeId>
            <Identifier>i=38</Identifier>
          </ReferenceTypeId>
          <IsInverse>false</IsInverse>
          <TargetId>
            <Identifier>ns=1;i=15012</Identifier>
          </TargetId>
        </ReferenceNode>
      </References>
      <IsAbstract>false</IsAbstract>
      <DataTypeDefinition i:nil="true" />
    </Node>
    <Node i:type="VariableNode">
      <NodeId>
        <Identifier>ns=1;i=15003</Identifier>
      </NodeId>
      <NodeClass>Variable_2</NodeClass>
      <BrowseName>
        <NamespaceIndex>1</NamespaceIndex>
        <Name>BoilerStatus</Name>
      </BrowseName>
      <DisplayName>
        <Locale></Locale>
        <Text>BoilerStatus</Text>
      </DisplayName>
      <Description i:nil="true" />
      <WriteMask>0</WriteMask>
      <UserWriteMask>0</UserWriteMask>
      <RolePermissions />
      <UserRolePermissions />
      <AccessRestrictions>0</AccessRestrictions>
      <References>
        <ReferenceNode>
          <ReferenceTypeId>
            <Identifier>i=47</Identifier>
          </ReferenceTypeId>
          <IsInverse>true</IsInverse>
          <TargetId>
            <Identifier>ns=1;i=15068</Identifier>
          </TargetId>
        </ReferenceNode>
        <ReferenceNode>
          <ReferenceTypeId>
            <Identifier>i=40</Identifier>
          </ReferenceTypeId>
          <IsInverse>false</IsInverse>
          <TargetId>
            <Identifier>i=63</Identifier>
          </TargetId>
        </ReferenceNode>
        <ReferenceNode>
          <ReferenceTypeId>
            <Identifier>i=37</Identifier>
          </ReferenceTypeId>
          <IsInverse>false</IsInverse>
          <TargetId>
            <Identifier>i=78</Identifier>
          </TargetId>
        </ReferenceNode>
      </References>
      <Value>
        <Value>
          <ExtensionObject xmlns="http://opcfoundation.org/UA/2008/02/Types.xsd">
            <TypeId>
              <Identifier>ns=1;i=15084</Identifier>
            </TypeId>
            <Body>
              <BoilerDataType xmlns="http://microsoft.com/Opc/OpcPlc/Boiler">
                <Temperature>
                  <Top>20</Top>
                  <Bottom>20</Bottom>
                </Temperature>
                <Pressure>100020</Pressure>
                <HeaterState>On</HeaterState>
              </BoilerDataType>
            </Body>
          </ExtensionObject>
        </Value>
      </Value>
      <DataType>
        <Identifier>ns=1;i=15032</Identifier>
      </DataType>
      <ValueRank>-1</ValueRank>
      <ArrayDimensions />
      <AccessLevel>1</AccessLevel>
      <UserAccessLevel>1</UserAccessLevel>
      <MinimumSamplingInterval>0</MinimumSamplingInterval>
      <Historizing>false</Historizing>
      <AccessLevelEx>0</AccessLevelEx>
    </Node>
    <Node i:type="ObjectNode">
      <NodeId>
        <Identifier>ns=1;i=15004</Identifier>
      </NodeId>
      <NodeClass>Object_1</NodeClass>
      <BrowseName>
        <NamespaceIndex>0</NamespaceIndex>
        <Name>Default Binary</Name>
      </BrowseName>
      <DisplayName>
        <Locale></Locale>
        <Text>Default Binary</Text>
      </DisplayName>
      <Description i:nil="true" />
      <WriteMask>0</WriteMask>
      <UserWriteMask>0</UserWriteMask>
      <RolePermissions />
      <UserRolePermissions />
      <AccessRestrictions>0</AccessRestrictions>
      <References>
        <ReferenceNode>
          <ReferenceTypeId>
            <Identifier>i=40</Identifier>
          </ReferenceTypeId>
          <IsInverse>false</IsInverse>
          <TargetId>
            <Identifier>i=76</Identifier>
          </TargetId>
        </ReferenceNode>
        <ReferenceNode>
          <ReferenceTypeId>
            <Identifier>i=38</Identifier>
          </ReferenceTypeId>
          <IsInverse>true</IsInverse>
          <TargetId>
            <Identifier>ns=1;i=15001</Identifier>
          </TargetId>
        </ReferenceNode>
        <ReferenceNode>
          <ReferenceTypeId>
            <Identifier>i=39</Identifier>
          </ReferenceTypeId>
          <IsInverse>false</IsInverse>
          <TargetId>
            <Identifier>ns=1;i=15005</Identifier>
          </TargetId>
        </ReferenceNode>
      </References>
      <EventNotifier>0</EventNotifier>
    </Node>
    <Node i:type="VariableNode">
      <NodeId>
        <Identifier>ns=1;i=15005</Identifier>
      </NodeId>
      <NodeClass>Variable_2</NodeClass>
      <BrowseName>
        <NamespaceIndex>1</NamespaceIndex>
        <Name>BoilerTemperatureType</Name>
      </BrowseName>
      <DisplayName>
        <Locale></Locale>
        <Text>BoilerTemperatureType</Text>
      </DisplayName>
      <Description i:nil="true" />
      <WriteMask>0</WriteMask>
      <UserWriteMask>0</UserWriteMask>
      <RolePermissions />
      <UserRolePermissions />
      <AccessRestrictions>0</AccessRestrictions>
      <References>
        <ReferenceNode>
          <ReferenceTypeId>
            <Identifier>i=47</Identifier>
          </ReferenceTypeId>
          <IsInverse>true</IsInverse>
          <TargetId>
            <Identifier>ns=1;i=15074</Identifier>
          </TargetId>
        </ReferenceNode>
        <ReferenceNode>
          <ReferenceTypeId>
            <Identifier>i=40</Identifier>
          </ReferenceTypeId>
          <IsInverse>false</IsInverse>
          <TargetId>
            <Identifier>i=69</Identifier>
          </TargetId>
        </ReferenceNode>
      </References>
      <Value>
        <Value>
          <String xmlns="http://opcfoundation.org/UA/2008/02/Types.xsd">BoilerTemperatureType</String>
        </Value>
      </Value>
      <DataType>
        <Identifier>i=12</Identifier>
      </DataType>
      <ValueRank>-1</ValueRank>
      <ArrayDimensions />
      <AccessLevel>1</AccessLevel>
      <UserAccessLevel>1</UserAccessLevel>
      <MinimumSamplingInterval>0</MinimumSamplingInterval>
      <Historizing>false</Historizing>
      <AccessLevelEx>0</AccessLevelEx>
    </Node>
    <Node i:type="ObjectNode">
      <NodeId>
        <Identifier>ns=1;i=15008</Identifier>
      </NodeId>
      <NodeClass>Object_1</NodeClass>
      <BrowseName>
        <NamespaceIndex>0</NamespaceIndex>
        <Name>Default XML</Name>
      </BrowseName>
      <DisplayName>
        <Locale></Locale>
        <Text>Default XML</Text>
      </DisplayName>
      <Description i:nil="true" />
      <WriteMask>0</WriteMask>
      <UserWriteMask>0</UserWriteMask>
      <RolePermissions />
      <UserRolePermissions />
      <AccessRestrictions>0</AccessRestrictions>
      <References>
        <ReferenceNode>
          <ReferenceTypeId>
            <Identifier>i=40</Identifier>
          </ReferenceTypeId>
          <IsInverse>false</IsInverse>
          <TargetId>
            <Identifier>i=76</Identifier>
          </TargetId>
        </ReferenceNode>
        <ReferenceNode>
          <ReferenceTypeId>
            <Identifier>i=38</Identifier>
          </ReferenceTypeId>
          <IsInverse>true</IsInverse>
          <TargetId>
            <Identifier>ns=1;i=15001</Identifier>
          </TargetId>
        </ReferenceNode>
        <ReferenceNode>
          <ReferenceTypeId>
            <Identifier>i=39</Identifier>
          </ReferenceTypeId>
          <IsInverse>false</IsInverse>
          <TargetId>
            <Identifier>ns=1;i=15009</Identifier>
          </TargetId>
        </ReferenceNode>
      </References>
      <EventNotifier>0</EventNotifier>
    </Node>
    <Node i:type="VariableNode">
      <NodeId>
        <Identifier>ns=1;i=15009</Identifier>
      </NodeId>
      <NodeClass>Variable_2</NodeClass>
      <BrowseName>
        <NamespaceIndex>1</NamespaceIndex>
        <Name>BoilerTemperatureType</Name>
      </BrowseName>
      <DisplayName>
        <Locale></Locale>
        <Text>BoilerTemperatureType</Text>
      </DisplayName>
      <Description i:nil="true" />
      <WriteMask>0</WriteMask>
      <UserWriteMask>0</UserWriteMask>
      <RolePermissions />
      <UserRolePermissions />
      <AccessRestrictions>0</AccessRestrictions>
      <References>
        <ReferenceNode>
          <ReferenceTypeId>
            <Identifier>i=47</Identifier>
          </ReferenceTypeId>
          <IsInverse>true</IsInverse>
          <TargetId>
            <Identifier>ns=1;i=15086</Identifier>
          </TargetId>
        </ReferenceNode>
        <ReferenceNode>
          <ReferenceTypeId>
            <Identifier>i=40</Identifier>
          </ReferenceTypeId>
          <IsInverse>false</IsInverse>
          <TargetId>
            <Identifier>i=69</Identifier>
          </TargetId>
        </ReferenceNode>
      </References>
      <Value>
        <Value>
          <String xmlns="http://opcfoundation.org/UA/2008/02/Types.xsd">//xs:element[@name='BoilerTemperatureType']</String>
        </Value>
      </Value>
      <DataType>
        <Identifier>i=12</Identifier>
      </DataType>
      <ValueRank>-1</ValueRank>
      <ArrayDimensions />
      <AccessLevel>1</AccessLevel>
      <UserAccessLevel>1</UserAccessLevel>
      <MinimumSamplingInterval>0</MinimumSamplingInterval>
      <Historizing>false</Historizing>
      <AccessLevelEx>0</AccessLevelEx>
    </Node>
    <Node i:type="ObjectNode">
      <NodeId>
        <Identifier>ns=1;i=15012</Identifier>
      </NodeId>
      <NodeClass>Object_1</NodeClass>
      <BrowseName>
        <NamespaceIndex>0</NamespaceIndex>
        <Name>Default JSON</Name>
      </BrowseName>
      <DisplayName>
        <Locale></Locale>
        <Text>Default JSON</Text>
      </DisplayName>
      <Description i:nil="true" />
      <WriteMask>0</WriteMask>
      <UserWriteMask>0</UserWriteMask>
      <RolePermissions />
      <UserRolePermissions />
      <AccessRestrictions>0</AccessRestrictions>
      <References>
        <ReferenceNode>
          <ReferenceTypeId>
            <Identifier>i=40</Identifier>
          </ReferenceTypeId>
          <IsInverse>false</IsInverse>
          <TargetId>
            <Identifier>i=76</Identifier>
          </TargetId>
        </ReferenceNode>
        <ReferenceNode>
          <ReferenceTypeId>
            <Identifier>i=38</Identifier>
          </ReferenceTypeId>
          <IsInverse>true</IsInverse>
          <TargetId>
            <Identifier>ns=1;i=15001</Identifier>
          </TargetId>
        </ReferenceNode>
      </References>
      <EventNotifier>0</EventNotifier>
    </Node>
    <Node i:type="VariableNode">
      <NodeId>
        <Identifier>ns=1;i=15013</Identifier>
      </NodeId>
      <NodeClass>Variable_2</NodeClass>
      <BrowseName>
        <NamespaceIndex>1</NamespaceIndex>
        <Name>BoilerStatus</Name>
      </BrowseName>
      <DisplayName>
        <Locale></Locale>
        <Text>BoilerStatus</Text>
      </DisplayName>
      <Description i:nil="true" />
      <WriteMask>0</WriteMask>
      <UserWriteMask>0</UserWriteMask>
      <RolePermissions />
      <UserRolePermissions />
      <AccessRestrictions>0</AccessRestrictions>
      <References>
        <ReferenceNode>
          <ReferenceTypeId>
            <Identifier>i=47</Identifier>
          </ReferenceTypeId>
          <IsInverse>true</IsInverse>
          <TargetId>
            <Identifier>ns=1;i=15070</Identifier>
          </TargetId>
        </ReferenceNode>
        <ReferenceNode>
          <ReferenceTypeId>
            <Identifier>i=40</Identifier>
          </ReferenceTypeId>
          <IsInverse>false</IsInverse>
          <TargetId>
            <Identifier>i=63</Identifier>
          </TargetId>
        </ReferenceNode>
      </References>
      <Value>
        <Value>
          <ExtensionObject xmlns="http://opcfoundation.org/UA/2008/02/Types.xsd">
            <TypeId>
              <Identifier>ns=1;i=15084</Identifier>
            </TypeId>
            <Body>
              <BoilerDataType xmlns="http://microsoft.com/Opc/OpcPlc/Boiler">
                <Temperature>
                  <Top>20</Top>
                  <Bottom>20</Bottom>
                </Temperature>
                <Pressure>100020</Pressure>
                <HeaterState>On</HeaterState>
              </BoilerDataType>
            </Body>
          </ExtensionObject>
        </Value>
      </Value>
      <DataType>
        <Identifier>ns=1;i=15032</Identifier>
      </DataType>
      <ValueRank>-1</ValueRank>
      <ArrayDimensions />
      <AccessLevel>1</AccessLevel>
      <UserAccessLevel>1</UserAccessLevel>
      <MinimumSamplingInterval>0</MinimumSamplingInterval>
      <Historizing>false</Historizing>
      <AccessLevelEx>0</AccessLevelEx>
    </Node>
    <Node i:type="DataTypeNode">
      <NodeId>
        <Identifier>ns=1;i=15014</Identifier>
      </NodeId>
      <NodeClass>DataType_64</NodeClass>
      <BrowseName>
        <NamespaceIndex>1</NamespaceIndex>
        <Name>BoilerHeaterStateType</Name>
      </BrowseName>
      <DisplayName>
        <Locale></Locale>
        <Text>BoilerHeaterStateType</Text>
      </DisplayName>
      <Description>
        <Locale></Locale>
        <Text>Heater working state.</Text>
      </Description>
      <WriteMask>0</WriteMask>
      <UserWriteMask>0</UserWriteMask>
      <RolePermissions />
      <UserRolePermissions />
      <AccessRestrictions>0</AccessRestrictions>
      <References>
        <ReferenceNode>
          <ReferenceTypeId>
            <Identifier>i=45</Identifier>
          </ReferenceTypeId>
          <IsInverse>true</IsInverse>
          <TargetId>
            <Identifier>i=29</Identifier>
          </TargetId>
        </ReferenceNode>
        <ReferenceNode>
          <ReferenceTypeId>
            <Identifier>i=46</Identifier>
          </ReferenceTypeId>
          <IsInverse>false</IsInverse>
          <TargetId>
            <Identifier>ns=1;i=15015</Identifier>
          </TargetId>
        </ReferenceNode>
      </References>
      <IsAbstract>false</IsAbstract>
      <DataTypeDefinition i:nil="true" />
    </Node>
    <Node i:type="VariableNode">
      <NodeId>
        <Identifier>ns=1;i=15015</Identifier>
      </NodeId>
      <NodeClass>Variable_2</NodeClass>
      <BrowseName>
        <NamespaceIndex>0</NamespaceIndex>
        <Name>EnumStrings</Name>
      </BrowseName>
      <DisplayName>
        <Locale></Locale>
        <Text>EnumStrings</Text>
      </DisplayName>
      <Description i:nil="true" />
      <WriteMask>0</WriteMask>
      <UserWriteMask>0</UserWriteMask>
      <RolePermissions />
      <UserRolePermissions />
      <AccessRestrictions>0</AccessRestrictions>
      <References>
        <ReferenceNode>
          <ReferenceTypeId>
            <Identifier>i=46</Identifier>
          </ReferenceTypeId>
          <IsInverse>true</IsInverse>
          <TargetId>
            <Identifier>ns=1;i=15014</Identifier>
          </TargetId>
        </ReferenceNode>
        <ReferenceNode>
          <ReferenceTypeId>
            <Identifier>i=40</Identifier>
          </ReferenceTypeId>
          <IsInverse>false</IsInverse>
          <TargetId>
            <Identifier>i=68</Identifier>
          </TargetId>
        </ReferenceNode>
        <ReferenceNode>
          <ReferenceTypeId>
            <Identifier>i=37</Identifier>
          </ReferenceTypeId>
          <IsInverse>false</IsInverse>
          <TargetId>
            <Identifier>i=78</Identifier>
          </TargetId>
        </ReferenceNode>
      </References>
      <Value>
        <Value>
          <ListOfLocalizedText xmlns="http://opcfoundation.org/UA/2008/02/Types.xsd">
            <LocalizedText>
              <Locale></Locale>
              <Text>Off</Text>
            </LocalizedText>
            <LocalizedText>
              <Locale></Locale>
              <Text>On</Text>
            </LocalizedText>
          </ListOfLocalizedText>
        </Value>
      </Value>
      <DataType>
        <Identifier>i=21</Identifier>
      </DataType>
      <ValueRank>1</ValueRank>
      <ArrayDimensions>
        <UInt32>0</UInt32>
      </ArrayDimensions>
      <AccessLevel>1</AccessLevel>
      <UserAccessLevel>1</UserAccessLevel>
      <MinimumSamplingInterval>0</MinimumSamplingInterval>
      <Historizing>false</Historizing>
      <AccessLevelEx>0</AccessLevelEx>
    </Node>
    <Node i:type="DataTypeNode">
      <NodeId>
        <Identifier>ns=1;i=15032</Identifier>
      </NodeId>
      <NodeClass>DataType_64</NodeClass>
      <BrowseName>
        <NamespaceIndex>1</NamespaceIndex>
        <Name>BoilerDataType</Name>
      </BrowseName>
      <DisplayName>
        <Locale></Locale>
        <Text>BoilerDataType</Text>
      </DisplayName>
      <Description>
        <Locale></Locale>
        <Text>Temperature in °C, pressure in Pa and heater state.</Text>
      </Description>
      <WriteMask>0</WriteMask>
      <UserWriteMask>0</UserWriteMask>
      <RolePermissions />
      <UserRolePermissions />
      <AccessRestrictions>0</AccessRestrictions>
      <References>
        <ReferenceNode>
          <ReferenceTypeId>
            <Identifier>i=45</Identifier>
          </ReferenceTypeId>
          <IsInverse>true</IsInverse>
          <TargetId>
            <Identifier>i=22</Identifier>
          </TargetId>
        </ReferenceNode>
        <ReferenceNode>
          <ReferenceTypeId>
            <Identifier>i=38</Identifier>
          </ReferenceTypeId>
          <IsInverse>false</IsInverse>
          <TargetId>
            <Identifier>ns=1;i=15072</Identifier>
          </TargetId>
        </ReferenceNode>
        <ReferenceNode>
          <ReferenceTypeId>
            <Identifier>i=38</Identifier>
          </ReferenceTypeId>
          <IsInverse>false</IsInverse>
          <TargetId>
            <Identifier>ns=1;i=15084</Identifier>
          </TargetId>
        </ReferenceNode>
        <ReferenceNode>
          <ReferenceTypeId>
            <Identifier>i=38</Identifier>
          </ReferenceTypeId>
          <IsInverse>false</IsInverse>
          <TargetId>
            <Identifier>ns=1;i=15096</Identifier>
          </TargetId>
        </ReferenceNode>
      </References>
      <IsAbstract>false</IsAbstract>
      <DataTypeDefinition i:nil="true" />
    </Node>
    <Node i:type="ObjectTypeNode">
      <NodeId>
        <Identifier>ns=1;i=15068</Identifier>
      </NodeId>
      <NodeClass>ObjectType_8</NodeClass>
      <BrowseName>
        <NamespaceIndex>1</NamespaceIndex>
        <Name>BoilerType</Name>
      </BrowseName>
      <DisplayName>
        <Locale></Locale>
        <Text>BoilerType</Text>
      </DisplayName>
      <Description i:nil="true" />
      <WriteMask>0</WriteMask>
      <UserWriteMask>0</UserWriteMask>
      <RolePermissions />
      <UserRolePermissions />
      <AccessRestrictions>0</AccessRestrictions>
      <References>
        <ReferenceNode>
          <ReferenceTypeId>
            <Identifier>i=45</Identifier>
          </ReferenceTypeId>
          <IsInverse>true</IsInverse>
          <TargetId>
            <Identifier>i=58</Identifier>
          </TargetId>
        </ReferenceNode>
        <ReferenceNode>
          <ReferenceTypeId>
            <Identifier>i=47</Identifier>
          </ReferenceTypeId>
          <IsInverse>false</IsInverse>
          <TargetId>
            <Identifier>ns=1;i=15003</Identifier>
          </TargetId>
        </ReferenceNode>
      </References>
      <IsAbstract>false</IsAbstract>
    </Node>
    <Node i:type="ObjectNode">
      <NodeId>
        <Identifier>ns=1;i=15070</Identifier>
      </NodeId>
      <NodeClass>Object_1</NodeClass>
      <BrowseName>
        <NamespaceIndex>1</NamespaceIndex>
        <Name>Boiler #1</Name>
      </BrowseName>
      <DisplayName>
        <Locale></Locale>
        <Text>Boiler #1</Text>
      </DisplayName>
      <Description>
        <Locale></Locale>
        <Text>A simple boiler.</Text>
      </Description>
      <WriteMask>0</WriteMask>
      <UserWriteMask>0</UserWriteMask>
      <RolePermissions />
      <UserRolePermissions />
      <AccessRestrictions>0</AccessRestrictions>
      <References>
        <ReferenceNode>
          <ReferenceTypeId>
            <Identifier>i=40</Identifier>
          </ReferenceTypeId>
          <IsInverse>false</IsInverse>
          <TargetId>
            <Identifier>ns=1;i=15068</Identifier>
          </TargetId>
        </ReferenceNode>
        <ReferenceNode>
          <ReferenceTypeId>
            <Identifier>i=35</Identifier>
          </ReferenceTypeId>
          <IsInverse>true</IsInverse>
          <TargetId>
            <Identifier>i=85</Identifier>
          </TargetId>
        </ReferenceNode>
        <ReferenceNode>
          <ReferenceTypeId>
            <Identifier>i=47</Identifier>
          </ReferenceTypeId>
          <IsInverse>false</IsInverse>
          <TargetId>
            <Identifier>ns=1;i=15013</Identifier>
          </TargetId>
        </ReferenceNode>
      </References>
      <EventNotifier>1</EventNotifier>
    </Node>
    <Node i:type="ObjectNode">
      <NodeId>
        <Identifier>ns=1;i=15072</Identifier>
      </NodeId>
      <NodeClass>Object_1</NodeClass>
      <BrowseName>
        <NamespaceIndex>0</NamespaceIndex>
        <Name>Default Binary</Name>
      </BrowseName>
      <DisplayName>
        <Locale></Locale>
        <Text>Default Binary</Text>
      </DisplayName>
      <Description i:nil="true" />
      <WriteMask>0</WriteMask>
      <UserWriteMask>0</UserWriteMask>
      <RolePermissions />
      <UserRolePermissions />
      <AccessRestrictions>0</AccessRestrictions>
      <References>
        <ReferenceNode>
          <ReferenceTypeId>
            <Identifier>i=40</Identifier>
          </ReferenceTypeId>
          <IsInverse>false</IsInverse>
          <TargetId>
            <Identifier>i=76</Identifier>
          </TargetId>
        </ReferenceNode>
        <ReferenceNode>
          <ReferenceTypeId>
            <Identifier>i=38</Identifier>
          </ReferenceTypeId>
          <IsInverse>true</IsInverse>
          <TargetId>
            <Identifier>ns=1;i=15032</Identifier>
          </TargetId>
        </ReferenceNode>
        <ReferenceNode>
          <ReferenceTypeId>
            <Identifier>i=39</Identifier>
          </ReferenceTypeId>
          <IsInverse>false</IsInverse>
          <TargetId>
            <Identifier>ns=1;i=15078</Identifier>
          </TargetId>
        </ReferenceNode>
      </References>
      <EventNotifier>0</EventNotifier>
    </Node>
    <Node i:type="VariableNode">
      <NodeId>
        <Identifier>ns=1;i=15074</Identifier>
      </NodeId>
      <NodeClass>Variable_2</NodeClass>
      <BrowseName>
        <NamespaceIndex>1</NamespaceIndex>
        <Name>BoilerModel</Name>
      </BrowseName>
      <DisplayName>
        <Locale></Locale>
        <Text>BoilerModel</Text>
      </DisplayName>
      <Description i:nil="true" />
      <WriteMask>0</WriteMask>
      <UserWriteMask>0</UserWriteMask>
      <RolePermissions />
      <UserRolePermissions />
      <AccessRestrictions>0</AccessRestrictions>
      <References>
        <ReferenceNode>
          <ReferenceTypeId>
            <Identifier>i=40</Identifier>
          </ReferenceTypeId>
          <IsInverse>false</IsInverse>
          <TargetId>
            <Identifier>i=72</Identifier>
          </TargetId>
        </ReferenceNode>
        <ReferenceNode>
          <ReferenceTypeId>
            <Identifier>i=47</Identifier>
          </ReferenceTypeId>
          <IsInverse>true</IsInverse>
          <TargetId>
            <Identifier>i=93</Identifier>
          </TargetId>
        </ReferenceNode>
        <ReferenceNode>
          <ReferenceTypeId>
            <Identifier>i=46</Identifier>
          </ReferenceTypeId>
          <IsInverse>false</IsInverse>
          <TargetId>
            <Identifier>ns=1;i=15076</Identifier>
          </TargetId>
        </ReferenceNode>
        <ReferenceNode>
          <ReferenceTypeId>
            <Identifier>i=46</Identifier>
          </ReferenceTypeId>
          <IsInverse>false</IsInverse>
          <TargetId>
            <Identifier>ns=1;i=15077</Identifier>
          </TargetId>
        </ReferenceNode>
        <ReferenceNode>
          <ReferenceTypeId>
            <Identifier>i=47</Identifier>
          </ReferenceTypeId>
          <IsInverse>false</IsInverse>
          <TargetId>
            <Identifier>ns=1;i=15078</Identifier>
          </TargetId>
        </ReferenceNode>
        <ReferenceNode>
          <ReferenceTypeId>
            <Identifier>i=47</Identifier>
          </ReferenceTypeId>
          <IsInverse>false</IsInverse>
          <TargetId>
            <Identifier>ns=1;i=15005</Identifier>
          </TargetId>
        </ReferenceNode>
      </References>
      <Value>
        <Value>
          <ByteString xmlns="http://opcfoundation.org/UA/2008/02/Types.xsd">PG9wYzpUeXBlRGljdGlvbmFyeQ0KICB4bWxuczpvcGM9Imh0dHA6Ly9vcGNmb3VuZGF0aW9uLm9y
Zy9CaW5hcnlTY2hlbWEvIg0KICB4bWxuczp4c2k9Imh0dHA6Ly93d3cudzMub3JnLzIwMDEvWE1M
U2NoZW1hLWluc3RhbmNlIg0KICB4bWxuczp1YT0iaHR0cDovL29wY2ZvdW5kYXRpb24ub3JnL1VB
LyINCiAgeG1sbnM6dG5zPSJodHRwOi8vbWljcm9zb2Z0LmNvbS9PcGMvT3BjUGxjL0JvaWxlciIN
CiAgRGVmYXVsdEJ5dGVPcmRlcj0iTGl0dGxlRW5kaWFuIg0KICBUYXJnZXROYW1lc3BhY2U9Imh0
dHA6Ly9taWNyb3NvZnQuY29tL09wYy9PcGNQbGMvQm9pbGVyIg0KPg0KICA8b3BjOkltcG9ydCBO
YW1lc3BhY2U9Imh0dHA6Ly9vcGNmb3VuZGF0aW9uLm9yZy9VQS8iIExvY2F0aW9uPSJPcGMuVWEu
QmluYXJ5U2NoZW1hLmJzZCIvPg0KDQogIDxvcGM6U3RydWN0dXJlZFR5cGUgTmFtZT0iQm9pbGVy
RGF0YVR5cGUiIEJhc2VUeXBlPSJ1YTpFeHRlbnNpb25PYmplY3QiPg0KICAgIDxvcGM6RG9jdW1l
bnRhdGlvbj5UZW1wZXJhdHVyZSBpbiDCsEMsIHByZXNzdXJlIGluIFBhIGFuZCBoZWF0ZXIgc3Rh
dGUuPC9vcGM6RG9jdW1lbnRhdGlvbj4NCiAgICA8b3BjOkZpZWxkIE5hbWU9IlRlbXBlcmF0dXJl
IiBUeXBlTmFtZT0idG5zOkJvaWxlclRlbXBlcmF0dXJlVHlwZSIgLz4NCiAgICA8b3BjOkZpZWxk
IE5hbWU9IlByZXNzdXJlIiBUeXBlTmFtZT0ib3BjOkludDMyIiAvPg0KICAgIDxvcGM6RmllbGQg
TmFtZT0iSGVhdGVyU3RhdGUiIFR5cGVOYW1lPSJ0bnM6Qm9pbGVySGVhdGVyU3RhdGVUeXBlIiAv
Pg0KICA8L29wYzpTdHJ1Y3R1cmVkVHlwZT4NCg0KICA8b3BjOlN0cnVjdHVyZWRUeXBlIE5hbWU9
IkJvaWxlclRlbXBlcmF0dXJlVHlwZSIgQmFzZVR5cGU9InVhOkV4dGVuc2lvbk9iamVjdCI+DQog
ICAgPG9wYzpEb2N1bWVudGF0aW9uPlRlbXBlcmF0dXJlIGluIMKwQyBuZXh0IHRvIHRoZSBoZWF0
ZXIgYXQgdGhlIGJvdHRvbSwgYW5kIGF3YXkgZnJvbSB0aGUgaGVhdGVyIGF0IHRoZSB0b3AuPC9v
cGM6RG9jdW1lbnRhdGlvbj4NCiAgICA8b3BjOkZpZWxkIE5hbWU9IlRvcCIgVHlwZU5hbWU9Im9w
YzpJbnQzMiIgLz4NCiAgICA8b3BjOkZpZWxkIE5hbWU9IkJvdHRvbSIgVHlwZU5hbWU9Im9wYzpJ
bnQzMiIgLz4NCiAgPC9vcGM6U3RydWN0dXJlZFR5cGU+DQoNCiAgPG9wYzpFbnVtZXJhdGVkVHlw
ZSBOYW1lPSJCb2lsZXJIZWF0ZXJTdGF0ZVR5cGUiIExlbmd0aEluQml0cz0iMzIiPg0KICAgIDxv
cGM6RG9jdW1lbnRhdGlvbj5IZWF0ZXIgd29ya2luZyBzdGF0ZS48L29wYzpEb2N1bWVudGF0aW9u
Pg0KICAgIDxvcGM6RW51bWVyYXRlZFZhbHVlIE5hbWU9Ik9mZiIgVmFsdWU9IjAiIC8+DQogICAg
PG9wYzpFbnVtZXJhdGVkVmFsdWUgTmFtZT0iT24iIFZhbHVlPSIxIiAvPg0KICA8L29wYzpFbnVt
ZXJhdGVkVHlwZT4NCg0KPC9vcGM6VHlwZURpY3Rpb25hcnk+</ByteString>
        </Value>
      </Value>
      <DataType>
        <Identifier>i=15</Identifier>
      </DataType>
      <ValueRank>-1</ValueRank>
      <ArrayDimensions />
      <AccessLevel>1</AccessLevel>
      <UserAccessLevel>1</UserAccessLevel>
      <MinimumSamplingInterval>0</MinimumSamplingInterval>
      <Historizing>false</Historizing>
      <AccessLevelEx>0</AccessLevelEx>
    </Node>
    <Node i:type="VariableNode">
      <NodeId>
        <Identifier>ns=1;i=15076</Identifier>
      </NodeId>
      <NodeClass>Variable_2</NodeClass>
      <BrowseName>
        <NamespaceIndex>0</NamespaceIndex>
        <Name>NamespaceUri</Name>
      </BrowseName>
      <DisplayName>
        <Locale></Locale>
        <Text>NamespaceUri</Text>
      </DisplayName>
      <Description i:nil="true" />
      <WriteMask>0</WriteMask>
      <UserWriteMask>0</UserWriteMask>
      <RolePermissions />
      <UserRolePermissions />
      <AccessRestrictions>0</AccessRestrictions>
      <References>
        <ReferenceNode>
          <ReferenceTypeId>
            <Identifier>i=46</Identifier>
          </ReferenceTypeId>
          <IsInverse>true</IsInverse>
          <TargetId>
            <Identifier>ns=1;i=15074</Identifier>
          </TargetId>
        </ReferenceNode>
        <ReferenceNode>
          <ReferenceTypeId>
            <Identifier>i=40</Identifier>
          </ReferenceTypeId>
          <IsInverse>false</IsInverse>
          <TargetId>
            <Identifier>i=68</Identifier>
          </TargetId>
        </ReferenceNode>
      </References>
      <Value>
        <Value>
          <String xmlns="http://opcfoundation.org/UA/2008/02/Types.xsd">http://microsoft.com/Opc/OpcPlc/Boiler</String>
        </Value>
      </Value>
      <DataType>
        <Identifier>i=12</Identifier>
      </DataType>
      <ValueRank>-1</ValueRank>
      <ArrayDimensions />
      <AccessLevel>1</AccessLevel>
      <UserAccessLevel>1</UserAccessLevel>
      <MinimumSamplingInterval>0</MinimumSamplingInterval>
      <Historizing>false</Historizing>
      <AccessLevelEx>0</AccessLevelEx>
    </Node>
    <Node i:type="VariableNode">
      <NodeId>
        <Identifier>ns=1;i=15077</Identifier>
      </NodeId>
      <NodeClass>Variable_2</NodeClass>
      <BrowseName>
        <NamespaceIndex>0</NamespaceIndex>
        <Name>Deprecated</Name>
      </BrowseName>
      <DisplayName>
        <Locale></Locale>
        <Text>Deprecated</Text>
      </DisplayName>
      <Description i:nil="true" />
      <WriteMask>0</WriteMask>
      <UserWriteMask>0</UserWriteMask>
      <RolePermissions />
      <UserRolePermissions />
      <AccessRestrictions>0</AccessRestrictions>
      <References>
        <ReferenceNode>
          <ReferenceTypeId>
            <Identifier>i=46</Identifier>
          </ReferenceTypeId>
          <IsInverse>true</IsInverse>
          <TargetId>
            <Identifier>ns=1;i=15074</Identifier>
          </TargetId>
        </ReferenceNode>
        <ReferenceNode>
          <ReferenceTypeId>
            <Identifier>i=40</Identifier>
          </ReferenceTypeId>
          <IsInverse>false</IsInverse>
          <TargetId>
            <Identifier>i=68</Identifier>
          </TargetId>
        </ReferenceNode>
      </References>
      <Value>
        <Value>
          <Boolean xmlns="http://opcfoundation.org/UA/2008/02/Types.xsd">true</Boolean>
        </Value>
      </Value>
      <DataType>
        <Identifier>i=1</Identifier>
      </DataType>
      <ValueRank>-1</ValueRank>
      <ArrayDimensions />
      <AccessLevel>1</AccessLevel>
      <UserAccessLevel>1</UserAccessLevel>
      <MinimumSamplingInterval>0</MinimumSamplingInterval>
      <Historizing>false</Historizing>
      <AccessLevelEx>0</AccessLevelEx>
    </Node>
    <Node i:type="VariableNode">
      <NodeId>
        <Identifier>ns=1;i=15078</Identifier>
      </NodeId>
      <NodeClass>Variable_2</NodeClass>
      <BrowseName>
        <NamespaceIndex>1</NamespaceIndex>
        <Name>BoilerDataType</Name>
      </BrowseName>
      <DisplayName>
        <Locale></Locale>
        <Text>BoilerDataType</Text>
      </DisplayName>
      <Description i:nil="true" />
      <WriteMask>0</WriteMask>
      <UserWriteMask>0</UserWriteMask>
      <RolePermissions />
      <UserRolePermissions />
      <AccessRestrictions>0</AccessRestrictions>
      <References>
        <ReferenceNode>
          <ReferenceTypeId>
            <Identifier>i=47</Identifier>
          </ReferenceTypeId>
          <IsInverse>true</IsInverse>
          <TargetId>
            <Identifier>ns=1;i=15074</Identifier>
          </TargetId>
        </ReferenceNode>
        <ReferenceNode>
          <ReferenceTypeId>
            <Identifier>i=40</Identifier>
          </ReferenceTypeId>
          <IsInverse>false</IsInverse>
          <TargetId>
            <Identifier>i=69</Identifier>
          </TargetId>
        </ReferenceNode>
      </References>
      <Value>
        <Value>
          <String xmlns="http://opcfoundation.org/UA/2008/02/Types.xsd">BoilerDataType</String>
        </Value>
      </Value>
      <DataType>
        <Identifier>i=12</Identifier>
      </DataType>
      <ValueRank>-1</ValueRank>
      <ArrayDimensions />
      <AccessLevel>1</AccessLevel>
      <UserAccessLevel>1</UserAccessLevel>
      <MinimumSamplingInterval>0</MinimumSamplingInterval>
      <Historizing>false</Historizing>
      <AccessLevelEx>0</AccessLevelEx>
    </Node>
    <Node i:type="ObjectNode">
      <NodeId>
        <Identifier>ns=1;i=15084</Identifier>
      </NodeId>
      <NodeClass>Object_1</NodeClass>
      <BrowseName>
        <NamespaceIndex>0</NamespaceIndex>
        <Name>Default XML</Name>
      </BrowseName>
      <DisplayName>
        <Locale></Locale>
        <Text>Default XML</Text>
      </DisplayName>
      <Description i:nil="true" />
      <WriteMask>0</WriteMask>
      <UserWriteMask>0</UserWriteMask>
      <RolePermissions />
      <UserRolePermissions />
      <AccessRestrictions>0</AccessRestrictions>
      <References>
        <ReferenceNode>
          <ReferenceTypeId>
            <Identifier>i=40</Identifier>
          </ReferenceTypeId>
          <IsInverse>false</IsInverse>
          <TargetId>
            <Identifier>i=76</Identifier>
          </TargetId>
        </ReferenceNode>
        <ReferenceNode>
          <ReferenceTypeId>
            <Identifier>i=38</Identifier>
          </ReferenceTypeId>
          <IsInverse>true</IsInverse>
          <TargetId>
            <Identifier>ns=1;i=15032</Identifier>
          </TargetId>
        </ReferenceNode>
        <ReferenceNode>
          <ReferenceTypeId>
            <Identifier>i=39</Identifier>
          </ReferenceTypeId>
          <IsInverse>false</IsInverse>
          <TargetId>
            <Identifier>ns=1;i=15090</Identifier>
          </TargetId>
        </ReferenceNode>
      </References>
      <EventNotifier>0</EventNotifier>
    </Node>
    <Node i:type="VariableNode">
      <NodeId>
        <Identifier>ns=1;i=15086</Identifier>
      </NodeId>
      <NodeClass>Variable_2</NodeClass>
      <BrowseName>
        <NamespaceIndex>1</NamespaceIndex>
        <Name>BoilerModel</Name>
      </BrowseName>
      <DisplayName>
        <Locale></Locale>
        <Text>BoilerModel</Text>
      </DisplayName>
      <Description i:nil="true" />
      <WriteMask>0</WriteMask>
      <UserWriteMask>0</UserWriteMask>
      <RolePermissions />
      <UserRolePermissions />
      <AccessRestrictions>0</AccessRestrictions>
      <References>
        <ReferenceNode>
          <ReferenceTypeId>
            <Identifier>i=40</Identifier>
          </ReferenceTypeId>
          <IsInverse>false</IsInverse>
          <TargetId>
            <Identifier>i=72</Identifier>
          </TargetId>
        </ReferenceNode>
        <ReferenceNode>
          <ReferenceTypeId>
            <Identifier>i=47</Identifier>
          </ReferenceTypeId>
          <IsInverse>true</IsInverse>
          <TargetId>
            <Identifier>i=92</Identifier>
          </TargetId>
        </ReferenceNode>
        <ReferenceNode>
          <ReferenceTypeId>
            <Identifier>i=46</Identifier>
          </ReferenceTypeId>
          <IsInverse>false</IsInverse>
          <TargetId>
            <Identifier>ns=1;i=15088</Identifier>
          </TargetId>
        </ReferenceNode>
        <ReferenceNode>
          <ReferenceTypeId>
            <Identifier>i=46</Identifier>
          </ReferenceTypeId>
          <IsInverse>false</IsInverse>
          <TargetId>
            <Identifier>ns=1;i=15089</Identifier>
          </TargetId>
        </ReferenceNode>
        <ReferenceNode>
          <ReferenceTypeId>
            <Identifier>i=47</Identifier>
          </ReferenceTypeId>
          <IsInverse>false</IsInverse>
          <TargetId>
            <Identifier>ns=1;i=15090</Identifier>
          </TargetId>
        </ReferenceNode>
        <ReferenceNode>
          <ReferenceTypeId>
            <Identifier>i=47</Identifier>
          </ReferenceTypeId>
          <IsInverse>false</IsInverse>
          <TargetId>
            <Identifier>ns=1;i=15009</Identifier>
          </TargetId>
        </ReferenceNode>
      </References>
      <Value>
        <Value>
          <ByteString xmlns="http://opcfoundation.org/UA/2008/02/Types.xsd">PHhzOnNjaGVtYQ0KICB4bWxuczp4cz0iaHR0cDovL3d3dy53My5vcmcvMjAwMS9YTUxTY2hlbWEi
DQogIHhtbG5zOnVhPSJodHRwOi8vb3BjZm91bmRhdGlvbi5vcmcvVUEvMjAwOC8wMi9UeXBlcy54
c2QiDQogIHhtbG5zOnRucz0iaHR0cDovL21pY3Jvc29mdC5jb20vT3BjL09wY1BsYy9Cb2lsZXIi
DQogIHRhcmdldE5hbWVzcGFjZT0iaHR0cDovL21pY3Jvc29mdC5jb20vT3BjL09wY1BsYy9Cb2ls
ZXIiDQogIGVsZW1lbnRGb3JtRGVmYXVsdD0icXVhbGlmaWVkIg0KPg0KICA8eHM6aW1wb3J0IG5h
bWVzcGFjZT0iaHR0cDovL29wY2ZvdW5kYXRpb24ub3JnL1VBLzIwMDgvMDIvVHlwZXMueHNkIiAv
Pg0KDQogIDx4czpjb21wbGV4VHlwZSBuYW1lPSJCb2lsZXJEYXRhVHlwZSI+DQogICAgPHhzOmFu
bm90YXRpb24+DQogICAgICA8eHM6ZG9jdW1lbnRhdGlvbj5UZW1wZXJhdHVyZSBpbiDCsEMsIHBy
ZXNzdXJlIGluIFBhIGFuZCBoZWF0ZXIgc3RhdGUuPC94czpkb2N1bWVudGF0aW9uPg0KICAgIDwv
eHM6YW5ub3RhdGlvbj4NCiAgICA8eHM6c2VxdWVuY2U+DQogICAgICA8eHM6ZWxlbWVudCBuYW1l
PSJUZW1wZXJhdHVyZSIgdHlwZT0idG5zOkJvaWxlclRlbXBlcmF0dXJlVHlwZSIgbWluT2NjdXJz
PSIwIiBuaWxsYWJsZT0idHJ1ZSIgLz4NCiAgICAgIDx4czplbGVtZW50IG5hbWU9IlByZXNzdXJl
IiB0eXBlPSJ4czppbnQiIG1pbk9jY3Vycz0iMCIgLz4NCiAgICAgIDx4czplbGVtZW50IG5hbWU9
IkhlYXRlclN0YXRlIiB0eXBlPSJ0bnM6Qm9pbGVySGVhdGVyU3RhdGVUeXBlIiBtaW5PY2N1cnM9
IjAiIC8+DQogICAgPC94czpzZXF1ZW5jZT4NCiAgPC94czpjb21wbGV4VHlwZT4NCiAgPHhzOmVs
ZW1lbnQgbmFtZT0iQm9pbGVyRGF0YVR5cGUiIHR5cGU9InRuczpCb2lsZXJEYXRhVHlwZSIgLz4N
Cg0KICA8eHM6Y29tcGxleFR5cGUgbmFtZT0iTGlzdE9mQm9pbGVyRGF0YVR5cGUiPg0KICAgIDx4
czpzZXF1ZW5jZT4NCiAgICAgIDx4czplbGVtZW50IG5hbWU9IkJvaWxlckRhdGFUeXBlIiB0eXBl
PSJ0bnM6Qm9pbGVyRGF0YVR5cGUiIG1pbk9jY3Vycz0iMCIgbWF4T2NjdXJzPSJ1bmJvdW5kZWQi
IG5pbGxhYmxlPSJ0cnVlIiAvPg0KICAgIDwveHM6c2VxdWVuY2U+DQogIDwveHM6Y29tcGxleFR5
cGU+DQogIDx4czplbGVtZW50IG5hbWU9Ikxpc3RPZkJvaWxlckRhdGFUeXBlIiB0eXBlPSJ0bnM6
TGlzdE9mQm9pbGVyRGF0YVR5cGUiIG5pbGxhYmxlPSJ0cnVlIj48L3hzOmVsZW1lbnQ+DQoNCiAg
PHhzOmNvbXBsZXhUeXBlIG5hbWU9IkJvaWxlclRlbXBlcmF0dXJlVHlwZSI+DQogICAgPHhzOmFu
bm90YXRpb24+DQogICAgICA8eHM6ZG9jdW1lbnRhdGlvbj5UZW1wZXJhdHVyZSBpbiDCsEMgbmV4
dCB0byB0aGUgaGVhdGVyIGF0IHRoZSBib3R0b20sIGFuZCBhd2F5IGZyb20gdGhlIGhlYXRlciBh
dCB0aGUgdG9wLjwveHM6ZG9jdW1lbnRhdGlvbj4NCiAgICA8L3hzOmFubm90YXRpb24+DQogICAg
PHhzOnNlcXVlbmNlPg0KICAgICAgPHhzOmVsZW1lbnQgbmFtZT0iVG9wIiB0eXBlPSJ4czppbnQi
IG1pbk9jY3Vycz0iMCIgLz4NCiAgICAgIDx4czplbGVtZW50IG5hbWU9IkJvdHRvbSIgdHlwZT0i
eHM6aW50IiBtaW5PY2N1cnM9IjAiIC8+DQogICAgPC94czpzZXF1ZW5jZT4NCiAgPC94czpjb21w
bGV4VHlwZT4NCiAgPHhzOmVsZW1lbnQgbmFtZT0iQm9pbGVyVGVtcGVyYXR1cmVUeXBlIiB0eXBl
PSJ0bnM6Qm9pbGVyVGVtcGVyYXR1cmVUeXBlIiAvPg0KDQogIDx4czpjb21wbGV4VHlwZSBuYW1l
PSJMaXN0T2ZCb2lsZXJUZW1wZXJhdHVyZVR5cGUiPg0KICAgIDx4czpzZXF1ZW5jZT4NCiAgICAg
IDx4czplbGVtZW50IG5hbWU9IkJvaWxlclRlbXBlcmF0dXJlVHlwZSIgdHlwZT0idG5zOkJvaWxl
clRlbXBlcmF0dXJlVHlwZSIgbWluT2NjdXJzPSIwIiBtYXhPY2N1cnM9InVuYm91bmRlZCIgbmls
bGFibGU9InRydWUiIC8+DQogICAgPC94czpzZXF1ZW5jZT4NCiAgPC94czpjb21wbGV4VHlwZT4N
CiAgPHhzOmVsZW1lbnQgbmFtZT0iTGlzdE9mQm9pbGVyVGVtcGVyYXR1cmVUeXBlIiB0eXBlPSJ0
bnM6TGlzdE9mQm9pbGVyVGVtcGVyYXR1cmVUeXBlIiBuaWxsYWJsZT0idHJ1ZSI+PC94czplbGVt
ZW50Pg0KDQogIDx4czpzaW1wbGVUeXBlICBuYW1lPSJCb2lsZXJIZWF0ZXJTdGF0ZVR5cGUiPg0K
ICAgIDx4czphbm5vdGF0aW9uPg0KICAgICAgPHhzOmRvY3VtZW50YXRpb24+SGVhdGVyIHdvcmtp
bmcgc3RhdGUuPC94czpkb2N1bWVudGF0aW9uPg0KICAgIDwveHM6YW5ub3RhdGlvbj4NCiAgICA8
eHM6cmVzdHJpY3Rpb24gYmFzZT0ieHM6c3RyaW5nIj4NCiAgICAgIDx4czplbnVtZXJhdGlvbiB2
YWx1ZT0iT2ZmXzAiIC8+DQogICAgICA8eHM6ZW51bWVyYXRpb24gdmFsdWU9Ik9uXzEiIC8+DQog
ICAgPC94czpyZXN0cmljdGlvbj4NCiAgPC94czpzaW1wbGVUeXBlPg0KICA8eHM6ZWxlbWVudCBu
YW1lPSJCb2lsZXJIZWF0ZXJTdGF0ZVR5cGUiIHR5cGU9InRuczpCb2lsZXJIZWF0ZXJTdGF0ZVR5
cGUiIC8+DQoNCiAgPHhzOmNvbXBsZXhUeXBlIG5hbWU9Ikxpc3RPZkJvaWxlckhlYXRlclN0YXRl
VHlwZSI+DQogICAgPHhzOnNlcXVlbmNlPg0KICAgICAgPHhzOmVsZW1lbnQgbmFtZT0iQm9pbGVy
SGVhdGVyU3RhdGVUeXBlIiB0eXBlPSJ0bnM6Qm9pbGVySGVhdGVyU3RhdGVUeXBlIiBtaW5PY2N1
cnM9IjAiIG1heE9jY3Vycz0idW5ib3VuZGVkIiAvPg0KICAgIDwveHM6c2VxdWVuY2U+DQogIDwv
eHM6Y29tcGxleFR5cGU+DQogIDx4czplbGVtZW50IG5hbWU9Ikxpc3RPZkJvaWxlckhlYXRlclN0
YXRlVHlwZSIgdHlwZT0idG5zOkxpc3RPZkJvaWxlckhlYXRlclN0YXRlVHlwZSIgbmlsbGFibGU9
InRydWUiPjwveHM6ZWxlbWVudD4NCg0KPC94czpzY2hlbWE+</ByteString>
        </Value>
      </Value>
      <DataType>
        <Identifier>i=15</Identifier>
      </DataType>
      <ValueRank>-1</ValueRank>
      <ArrayDimensions />
      <AccessLevel>1</AccessLevel>
      <UserAccessLevel>1</UserAccessLevel>
      <MinimumSamplingInterval>0</MinimumSamplingInterval>
      <Historizing>false</Historizing>
      <AccessLevelEx>0</AccessLevelEx>
    </Node>
    <Node i:type="VariableNode">
      <NodeId>
        <Identifier>ns=1;i=15088</Identifier>
      </NodeId>
      <NodeClass>Variable_2</NodeClass>
      <BrowseName>
        <NamespaceIndex>0</NamespaceIndex>
        <Name>NamespaceUri</Name>
      </BrowseName>
      <DisplayName>
        <Locale></Locale>
        <Text>NamespaceUri</Text>
      </DisplayName>
      <Description i:nil="true" />
      <WriteMask>0</WriteMask>
      <UserWriteMask>0</UserWriteMask>
      <RolePermissions />
      <UserRolePermissions />
      <AccessRestrictions>0</AccessRestrictions>
      <References>
        <ReferenceNode>
          <ReferenceTypeId>
            <Identifier>i=46</Identifier>
          </ReferenceTypeId>
          <IsInverse>true</IsInverse>
          <TargetId>
            <Identifier>ns=1;i=15086</Identifier>
          </TargetId>
        </ReferenceNode>
        <ReferenceNode>
          <ReferenceTypeId>
            <Identifier>i=40</Identifier>
          </ReferenceTypeId>
          <IsInverse>false</IsInverse>
          <TargetId>
            <Identifier>i=68</Identifier>
          </TargetId>
        </ReferenceNode>
      </References>
      <Value>
        <Value>
          <String xmlns="http://opcfoundation.org/UA/2008/02/Types.xsd">http://microsoft.com/Opc/OpcPlc/Boiler</String>
        </Value>
      </Value>
      <DataType>
        <Identifier>i=12</Identifier>
      </DataType>
      <ValueRank>-1</ValueRank>
      <ArrayDimensions />
      <AccessLevel>1</AccessLevel>
      <UserAccessLevel>1</UserAccessLevel>
      <MinimumSamplingInterval>0</MinimumSamplingInterval>
      <Historizing>false</Historizing>
      <AccessLevelEx>0</AccessLevelEx>
    </Node>
    <Node i:type="VariableNode">
      <NodeId>
        <Identifier>ns=1;i=15089</Identifier>
      </NodeId>
      <NodeClass>Variable_2</NodeClass>
      <BrowseName>
        <NamespaceIndex>0</NamespaceIndex>
        <Name>Deprecated</Name>
      </BrowseName>
      <DisplayName>
        <Locale></Locale>
        <Text>Deprecated</Text>
      </DisplayName>
      <Description i:nil="true" />
      <WriteMask>0</WriteMask>
      <UserWriteMask>0</UserWriteMask>
      <RolePermissions />
      <UserRolePermissions />
      <AccessRestrictions>0</AccessRestrictions>
      <References>
        <ReferenceNode>
          <ReferenceTypeId>
            <Identifier>i=46</Identifier>
          </ReferenceTypeId>
          <IsInverse>true</IsInverse>
          <TargetId>
            <Identifier>ns=1;i=15086</Identifier>
          </TargetId>
        </ReferenceNode>
        <ReferenceNode>
          <ReferenceTypeId>
            <Identifier>i=40</Identifier>
          </ReferenceTypeId>
          <IsInverse>false</IsInverse>
          <TargetId>
            <Identifier>i=68</Identifier>
          </TargetId>
        </ReferenceNode>
      </References>
      <Value>
        <Value>
          <Boolean xmlns="http://opcfoundation.org/UA/2008/02/Types.xsd">true</Boolean>
        </Value>
      </Value>
      <DataType>
        <Identifier>i=1</Identifier>
      </DataType>
      <ValueRank>-1</ValueRank>
      <ArrayDimensions />
      <AccessLevel>1</AccessLevel>
      <UserAccessLevel>1</UserAccessLevel>
      <MinimumSamplingInterval>0</MinimumSamplingInterval>
      <Historizing>false</Historizing>
      <AccessLevelEx>0</AccessLevelEx>
    </Node>
    <Node i:type="VariableNode">
      <NodeId>
        <Identifier>ns=1;i=15090</Identifier>
      </NodeId>
      <NodeClass>Variable_2</NodeClass>
      <BrowseName>
        <NamespaceIndex>1</NamespaceIndex>
        <Name>BoilerDataType</Name>
      </BrowseName>
      <DisplayName>
        <Locale></Locale>
        <Text>BoilerDataType</Text>
      </DisplayName>
      <Description i:nil="true" />
      <WriteMask>0</WriteMask>
      <UserWriteMask>0</UserWriteMask>
      <RolePermissions />
      <UserRolePermissions />
      <AccessRestrictions>0</AccessRestrictions>
      <References>
        <ReferenceNode>
          <ReferenceTypeId>
            <Identifier>i=47</Identifier>
          </ReferenceTypeId>
          <IsInverse>true</IsInverse>
          <TargetId>
            <Identifier>ns=1;i=15086</Identifier>
          </TargetId>
        </ReferenceNode>
        <ReferenceNode>
          <ReferenceTypeId>
            <Identifier>i=40</Identifier>
          </ReferenceTypeId>
          <IsInverse>false</IsInverse>
          <TargetId>
            <Identifier>i=69</Identifier>
          </TargetId>
        </ReferenceNode>
      </References>
      <Value>
        <Value>
          <String xmlns="http://opcfoundation.org/UA/2008/02/Types.xsd">//xs:element[@name='BoilerDataType']</String>
        </Value>
      </Value>
      <DataType>
        <Identifier>i=12</Identifier>
      </DataType>
      <ValueRank>-1</ValueRank>
      <ArrayDimensions />
      <AccessLevel>1</AccessLevel>
      <UserAccessLevel>1</UserAccessLevel>
      <MinimumSamplingInterval>0</MinimumSamplingInterval>
      <Historizing>false</Historizing>
      <AccessLevelEx>0</AccessLevelEx>
    </Node>
    <Node i:type="ObjectNode">
      <NodeId>
        <Identifier>ns=1;i=15096</Identifier>
      </NodeId>
      <NodeClass>Object_1</NodeClass>
      <BrowseName>
        <NamespaceIndex>0</NamespaceIndex>
        <Name>Default JSON</Name>
      </BrowseName>
      <DisplayName>
        <Locale></Locale>
        <Text>Default JSON</Text>
      </DisplayName>
      <Description i:nil="true" />
      <WriteMask>0</WriteMask>
      <UserWriteMask>0</UserWriteMask>
      <RolePermissions />
      <UserRolePermissions />
      <AccessRestrictions>0</AccessRestrictions>
      <References>
        <ReferenceNode>
          <ReferenceTypeId>
            <Identifier>i=40</Identifier>
          </ReferenceTypeId>
          <IsInverse>false</IsInverse>
          <TargetId>
            <Identifier>i=76</Identifier>
          </TargetId>
        </ReferenceNode>
        <ReferenceNode>
          <ReferenceTypeId>
            <Identifier>i=38</Identifier>
          </ReferenceTypeId>
          <IsInverse>true</IsInverse>
          <TargetId>
            <Identifier>ns=1;i=15032</Identifier>
          </TargetId>
        </ReferenceNode>
      </References>
      <EventNotifier>0</EventNotifier>
    </Node>
  </Nodes>
</NodeSet>